gx_pollux-0.1a2.data/scripts/pollux
gx_pollux-0.1a2.data/scripts/pollux-pip
pollux/__init__.py
pollux/cli.py
pollux/inputer.py
pollux/license.py
pollux/pip/__init__.py
pollux/pip/cli.py
pollux/pip/utils.py
gx_pollux-0.1a2.dist-info/LICENSE
gx_pollux-0.1a2.dist-info/METADATA
gx_pollux-0.1a2.dist-info/WHEEL
gx_pollux-0.1a2.dist-info/top_level.txt
gx_pollux-0.1a2.dist-info/RECORD
