Metadata-Version: 2.1
Name: gx-pollux
Version: 0.1a2
Summary: pollux is the β Geminorum
Home-page: UNKNOWN
Author: gawainx
Author-email: liangyi@bupt.edu.cn
License: UNKNOWN
Platform: UNKNOWN
Classifier: Programming Language :: Python :: 3.8
Classifier: License :: OSI Approved :: GNU General Public License v3 (GPLv3)
Classifier: Operating System :: OS Independent
Requires-Dist: typer
